ALU.v
`timescale 1ns / 1ps

module ALU(
    input [31:0] A,
    input [31:0] B,
    input [3:0] ALUControl,
    output reg [31:0] Result,
    output Zero
);

    // Zero flag: goes high when Result is zero
    assign Zero = (Result == 32'b0);

    always @(*) begin
        case (ALUControl)
            4'b0010: Result = A + B;  // ADD
            4'b0110: Result = A - B;  // SUB
            4'b0000: Result = A & B;  // AND
            4'b0001: Result = A | B;  // OR
            // Additional operations...
            default: Result = 32'b0;  // Default 
        endcase
    end
endmodule

ALU_tb-2.v
`timescale 1ns / 1ps

module ALU_tb;

    // Testbench signals
    reg [31:0] A, B;
    reg [3:0] ALUControl;
    wire [31:0] Result;
    wire Zero;

    // Instantiate the ALU module
    ALU uut (
        .A(A),
        .B(B),
        .ALUControl(ALUControl),
        .Result(Result),
        .Zero(Zero)
    );

    // Test procedure
    initial begin
        // Dump waveforms to VCD file
        $dumpfile("ALU_waveform.vcd"); // Specify VCD file name
        $dumpvars(0, ALU_tb);         // Dump all variables in ALU_tb scope

        // Monitor output in the terminal
        $monitor("Time = %0t | A = %h | B = %h | ALUControl = %b | Result = %h | Zero = %b", 
                 $time, A, B, ALUControl, Result, Zero);

        // Test Case 1: ADD (A + B)
        A = 32'h00000010;  // 16
        B = 32'h00000020;  // 32
        ALUControl = 4'b0010;  // ADD
        #10;

        // Test Case 2: SUB (A - B)
        A = 32'h00000030;  // 48
        B = 32'h00000010;  // 16
        ALUControl = 4'b0110;  // SUB
        #10;

        // Test Case 3: AND (A & B)
        A = 32'hF0F0F0F0;
        B = 32'h0F0F0F0F;
        ALUControl = 4'b0000;  // AND
        #10;

        // Test Case 4: OR (A | B)
        A = 32'hF0F0F0F0;
        B = 32'h0F0F0F0F;
        ALUControl = 4'b0001;  // OR
        #10;

        // Test Case 5: XOR (A ^ B)
        A = 32'hF0F0F0F0;
        B = 32'h0F0F0F0F;
        ALUControl = 4'b0011;  // XOR
        #10;

        // Test Case 6: Logical Shift Left
        A = 32'h00000001;
        B = 32'h00000002;
        ALUControl = 4'b1000;  // SLL
        #10;

        // Test Case 7: Logical Shift Right
        A = 32'h00000010;
        B = 32'h00000002;
        ALUControl = 4'b1001;  // SRL
        #10;

        // Test Case 8: Arithmetic Shift Right
        A = 32'hF0000000;  // Negative number in two's complement
        B = 32'h00000004;
        ALUControl = 4'b1010;  // ASR
        #10;

        // Test Case 9: Default case
        A = 32'h00000001;
        B = 32'h00000001;
        ALUControl = 4'b1111;  // Undefined operation
        #10;

        // Stop simulation
        $stop;
    end
endmodule

ALU_waveform.vcd
$date
	Mon Nov 18 15:45:16 2024
$end
$version
	Icarus Verilog
$end
$timescale
	1ps
$end
$scope module ALU_tb $end
$var wire 1 ! Zero $end
$var wire 32 " Result [31:0] $end
$var reg 32 # A [31:0] $end
$var reg 4 $ ALUControl [3:0] $end
$var reg 32 % B [31:0] $end
$scope module uut $end
$var wire 32 & A [31:0] $end
$var wire 4 ' ALUControl [3:0] $end
$var wire 32 ( B [31:0] $end
$var wire 1 ! Zero $end
$var reg 32 ) Result [31:0] $end
$upscope $end
$upscope $end
$enddefinitions $end
$comment Show the parameter values. $end
$dumpall
$end
#0
$dumpvars
b110000 )
b100000 (
b10 '
b10000 &
b100000 %
b10 $
b10000 #
b110000 "
0!
$end
#10000
b100000 "
b100000 )
b110 $
b110 '
b10000 %
b10000 (
b110000 #
b110000 &
#20000
1!
b0 "
b0 )
b0 $
b0 '
b1111000011110000111100001111 %
b1111000011110000111100001111 (
b11110000111100001111000011110000 #
b11110000111100001111000011110000 &
#30000
0!
b11111111111111111111111111111111 "
b11111111111111111111111111111111 )
b1 $
b1 '
#40000
1!
b0 "
b0 )
b11 $
b11 '
#50000
b1000 $
b1000 '
b10 %
b10 (
b1 #
b1 &
#60000
b1001 $
b1001 '
b10000 #
b10000 &
#70000
b1010 $
b1010 '
b100 %
b100 (
b11110000000000000000000000000000 #
b11110000000000000000000000000000 &
#80000
b1111 $
b1111 '
b1 %
b1 (
b1 #
b1 &
